pywjs/__init__.py
pywjs/wbs/__init__.py
pywjs/wbs/allowed_func.py
pywjs/wbs/cache.py
pywjs/wbs/handle.py
pywjs/wbs/logger.py
pywjs/wbs/schema.py
pywjs/wbs/server.py
pywjs/wbs/subscribe.py
readme.md
pywjs-0.0.6.dist-info/WHEEL
pywjs-0.0.6.dist-info/METADATA
pywjs-0.0.6.dist-info/RECORD
