Metadata-Version: 2.1
Name: pywjs
Version: 0.0.6
Summary: 
Home-page: https://github.com/denisxab/py_wjs
Author: Denis Vetkin
Requires-Python: >=3.10
Classifier: Programming Language :: Python :: 3
Classifier: Programming Language :: Python :: 3.10
Classifier: Programming Language :: Python :: 3.11
Requires-Dist: aiosqlite (>=0.17.0,<0.18.0)
Requires-Dist: jsonpickle (==2.2.0)
Requires-Dist: logsmal (==0.0.14)
Requires-Dist: pydantic (>=1.10.2,<2.0.0)
Requires-Dist: websockets (>=10.4,<11.0)
Project-URL: Repository, https://github.com/denisxab/py_wjs
